haohaninfo/__init__.py
haohaninfo/version.cp39-win32.pyd
haohaninfo/GOrder/GOCommand.cp39-win32.pyd
haohaninfo/GOrder/GOGetKBar.cp39-win32.pyd
haohaninfo/GOrder/GOQuote.cp39-win32.pyd
haohaninfo/GOrder/__init__.py
haohaninfo/GOrder/kbar.cp39-win32.pyd
haohaninfo/MarketInfo/GetMarketInfo.cp39-win32.pyd
haohaninfo/MarketInfo/__init__.py
haohaninfo/MicroPlay/MicroPlayCommand.cp39-win32.pyd
haohaninfo/MicroPlay/MicroPlayQuote.cp39-win32.pyd
haohaninfo/MicroPlay/__init__.py
haohaninfo/MicroTest/MicroTest.cp39-win32.pyd
haohaninfo/MicroTest/__init__.py
haohaninfo/MicroTest/microtest_db.cp39-win32.pyd
haohaninfo-0.2.23.dist-info/METADATA
haohaninfo-0.2.23.dist-info/WHEEL
haohaninfo-0.2.23.dist-info/top_level.txt
haohaninfo-0.2.23.dist-info/RECORD
