Metadata-Version: 2.1
Name: haohaninfo
Version: 0.2.23
Summary: GOrder command for Windows
Home-page: UNKNOWN
Author: haohaninfo
Author-email: haohanservice@haohaninfo.com
License: UNKNOWN
Platform: UNKNOWN
Classifier: Programming Language :: Python :: 3.7
Classifier: Programming Language :: Python :: 3.8
Classifier: Operating System :: Microsoft :: Windows
Requires-Dist: zmq
Requires-Dist: requests
Requires-Dist: numpy
Requires-Dist: python-dateutil
Requires-Dist: pandas
